pip/__init__.py
pip/main.py
dero_pip-1.0.1.dist-info/METADATA
dero_pip-1.0.1.dist-info/WHEEL
dero_pip-1.0.1.dist-info/entry_points.txt
dero_pip-1.0.1.dist-info/top_level.txt
dero_pip-1.0.1.dist-info/RECORD
