Metadata-Version: 2.1
Name: dero-pip
Version: 1.0.1
Summary: CloudMiner custom pip
